MANIFEST.in
README.rst
setup.py
docs/HISTORY.txt
docs/INSTALL.txt
docs/LICENSE.GPL
docs/LICENSE.txt
ftw/__init__.py
ftw.permissionmanager.egg-info/PKG-INFO
ftw.permissionmanager.egg-info/SOURCES.txt
ftw.permissionmanager.egg-info/dependency_links.txt
ftw.permissionmanager.egg-info/entry_points.txt
ftw.permissionmanager.egg-info/namespace_packages.txt
ftw.permissionmanager.egg-info/not-zip-safe
ftw.permissionmanager.egg-info/requires.txt
ftw.permissionmanager.egg-info/top_level.txt
ftw/permissionmanager/__init__.py
ftw/permissionmanager/configure.zcml
ftw/permissionmanager/hooks.py
ftw/permissionmanager/indexer.py
ftw/permissionmanager/interfaces.py
ftw/permissionmanager/testing.py
ftw/permissionmanager/treeifier.py
ftw/permissionmanager/utils.py
ftw/permissionmanager/Extensions/install.py
ftw/permissionmanager/browser/__init__.py
ftw/permissionmanager/browser/configure.zcml
ftw/permissionmanager/browser/copy_permissions.py
ftw/permissionmanager/browser/import_export_permissions.py
ftw/permissionmanager/browser/permissionmanager.py
ftw/permissionmanager/browser/principal_role_tree.py
ftw/permissionmanager/browser/remove_permissions.py
ftw/permissionmanager/browser/sharing.py
ftw/permissionmanager/browser/resources/userroletree.js
ftw/permissionmanager/browser/select2-3.4.5/LICENSE
ftw/permissionmanager/browser/select2-3.4.5/README.md
ftw/permissionmanager/browser/select2-3.4.5/bower.json
ftw/permissionmanager/browser/select2-3.4.5/release.sh
ftw/permissionmanager/browser/select2-3.4.5/select2-bootstrap.css
ftw/permissionmanager/browser/select2-3.4.5/select2-spinner.gif
ftw/permissionmanager/browser/select2-3.4.5/select2.css
ftw/permissionmanager/browser/select2-3.4.5/select2.jquery.json
ftw/permissionmanager/browser/select2-3.4.5/select2.js
ftw/permissionmanager/browser/select2-3.4.5/select2.min.js
ftw/permissionmanager/browser/select2-3.4.5/select2.png
ftw/permissionmanager/browser/select2-3.4.5/select2_locale_ar.js
ftw/permissionmanager/browser/select2-3.4.5/select2_locale_bg.js
ftw/permissionmanager/browser/select2-3.4.5/select2_locale_ca.js
ftw/permissionmanager/browser/select2-3.4.5/select2_locale_cs.js
ftw/permissionmanager/browser/select2-3.4.5/select2_locale_da.js
ftw/permissionmanager/browser/select2-3.4.5/select2_locale_de.js
ftw/permissionmanager/browser/select2-3.4.5/select2_locale_el.js
