Metadata-Version: 2.1
Name: ftw.permissionmanager
Version: 3.0.2
Summary: UNKNOWN
Home-page: https://github.com/4teamwork/ftw.permissionmanager
Author: 4teamwork AG
Author-email: mailto:info@4teamwork.ch
Maintainer: Mathias Leimgruber
License: GPL2
Platform: UNKNOWN
Classifier: Framework :: Plone
Classifier: Framework :: Plone :: 4.3
Classifier: Framework :: Plone :: 5.1
Classifier: Programming Language :: Python
Classifier: Topic :: Software Development :: Libraries :: Python Modules
Provides-Extra: tests
